django_google_structured_logger/__init__.py
django_google_structured_logger/apps.py
django_google_structured_logger/constants.py
django_google_structured_logger/formatter.py
django_google_structured_logger/graphene_middlewares.py
django_google_structured_logger/middlewares.py
django_google_structured_logger/settings.py
django_google_structured_logger/storages.py
django_google_structured_logger-2.8.11.dist-info/licenses/LICENSE
django_google_structured_logger-2.8.11.dist-info/METADATA
django_google_structured_logger-2.8.11.dist-info/WHEEL
django_google_structured_logger-2.8.11.dist-info/top_level.txt
django_google_structured_logger-2.8.11.dist-info/RECORD
