Metadata-Version: 2.4
Name: django-google-structured-logger
Version: 2.8.11
Summary: Plugin for django to support  Google Structured Logger
Home-page: https://github.com/muehlemann-popp/django-google-structured-logger
Author: Farruh Sheripov
Author-email: Farruh Sheripov <sheripov.farruh@gmail.com>
Maintainer: Silvan Mühlemann
Maintainer-email: silvan.muehlemann@muehlemann-popp.ch
Requires-Python: >=3.9
License-File: LICENSE
Requires-Dist: python-json-logger<3,>=2.0.7
Requires-Dist: contextvars~=2.4
Requires-Dist: django<6,>=3
Requires-Dist: setuptools-scm<8,>=7.1.0
Dynamic: license-file
